PyPowerFlex/__init__.py
PyPowerFlex/base_client.py
PyPowerFlex/configuration.py
PyPowerFlex/constants.py
PyPowerFlex/exceptions.py
PyPowerFlex/powerflex_token.py
PyPowerFlex/utils.py
PyPowerFlex/objects/common/__init__.py
PyPowerFlex/objects/common/deployment.py
PyPowerFlex/objects/common/firmware_repository.py
PyPowerFlex/objects/common/host.py
PyPowerFlex/objects/common/managed_device.py
PyPowerFlex/objects/common/sdc.py
PyPowerFlex/objects/common/sdt.py
PyPowerFlex/objects/common/service_template.py
PyPowerFlex/objects/common/system.py
PyPowerFlex/objects/common/utility.py
PyPowerFlex/objects/gen1/__init__.py
PyPowerFlex/objects/gen1/acceleration_pool.py
PyPowerFlex/objects/gen1/device.py
PyPowerFlex/objects/gen1/fault_set.py
PyPowerFlex/objects/gen1/protection_domain.py
PyPowerFlex/objects/gen1/replication_consistency_group.py
PyPowerFlex/objects/gen1/replication_pair.py
PyPowerFlex/objects/gen1/sds.py
PyPowerFlex/objects/gen1/snapshot_policy.py
PyPowerFlex/objects/gen1/storage_pool.py
PyPowerFlex/objects/gen1/system.py
PyPowerFlex/objects/gen1/volume.py
PyPowerFlex/objects/gen2/__init__.py
PyPowerFlex/objects/gen2/device.py
PyPowerFlex/objects/gen2/device_group.py
PyPowerFlex/objects/gen2/protection_domain.py
PyPowerFlex/objects/gen2/snapshot_policy.py
PyPowerFlex/objects/gen2/storage_node.py
PyPowerFlex/objects/gen2/storage_pool.py
PyPowerFlex/objects/gen2/system.py
PyPowerFlex/objects/gen2/volume.py
pypowerflex-2.0.0.dist-info/licenses/LICENSE
pypowerflex-2.0.0.dist-info/METADATA
pypowerflex-2.0.0.dist-info/WHEEL
pypowerflex-2.0.0.dist-info/top_level.txt
pypowerflex-2.0.0.dist-info/RECORD
